odoo/addons/web_set_single_page_hidden/README.rst
odoo/addons/web_set_single_page_hidden/__init__.py
odoo/addons/web_set_single_page_hidden/__manifest__.py
odoo/addons/web_set_single_page_hidden/i18n/pt_BR.po
odoo/addons/web_set_single_page_hidden/i18n/web_set_single_page_hidden.pot
odoo/addons/web_set_single_page_hidden/readme/CONTRIBUTORS.rst
odoo/addons/web_set_single_page_hidden/readme/DESCRIPTION.rst
odoo/addons/web_set_single_page_hidden/static/description/icon.png
odoo/addons/web_set_single_page_hidden/static/description/index.html
odoo/addons/web_set_single_page_hidden/static/src/js/pager.js
odoo/addons/web_set_single_page_hidden/static/src/js/relational_fields.js
odoo/addons/web_set_single_page_hidden/views/webclient_templates.xml
odoo13_addon_web_set_single_page_hidden-13.0.1.0.1.dev4.dist-info/METADATA
odoo13_addon_web_set_single_page_hidden-13.0.1.0.1.dev4.dist-info/WHEEL
odoo13_addon_web_set_single_page_hidden-13.0.1.0.1.dev4.dist-info/top_level.txt
odoo13_addon_web_set_single_page_hidden-13.0.1.0.1.dev4.dist-info/RECORD
